regg.v
module regg(
    input ck,
    input rst,
    input [15:0] v,
    input l,
    output reg [15:0] r
);

    parameter Zero = 16'b0000000000000000;

    always @ (posedge ck) begin
        
        if(rst == 1) begin
            r = Zero;
        end

        if(l == 1) begin
            r = v;
        end
        
    end
    

endmodule

ula.v
module ula(
    input [15:0] v1,
    input [15:0] v2,
    input h,
    output reg overflow,
    output reg [15:0] r
);

    always @ (h or v1 or v2) begin
        case(h)
            1'b0 : {overflow, r} = v1 + v2;
            1'b1 : {overflow, r} = v1 * v2;
        endcase
    end

endmodule

mux.v
module mux(
    input [15:0] a,
    input [15:0] b,
    input [15:0] c,
    input [15:0] d,
    input [1:0] sel,
    output reg [15:0] out
);

    always @ (a or b or c or d or sel) begin
        case(sel)
            2'b00 : out = a;
            2'b01 : out = b;
            2'b10 : out = c;
            2'b11 : out = d;
        endcase
    end

endmodule

operativo.v
module operativo (
    input ck,
    input rst,
    input lx,
    input [1:0] m0,
    input [1:0] m1,
    input [1:0] m2,
    input h,
    input ls,
    input lh,
    input [15:0] X,
    input [15:0] A,
    input [15:0] B,
    input [15:0] C,
    input pronto,
    output overflow,
    output [15:0] resultado
);

    wire [15:0] RegX, RegS, RegH, res;
    wire [15:0] outm0, outm1, outm2;
    
    parameter Zero = 16'b0000000000000000;

    regg R1(ck, rst, X, lx, RegX);

    mux M0(Zero, A, B, C, m0, outm0);
    mux M1(outm0, RegX, RegS, RegH, m1, outm1);
    mux M2(RegX, outm0, RegS, RegH, m2, outm2);
    
    ula U(outm1, outm2, h, overflow, res);
    
    regg R2(ck, rst, res, lh, RegH);
    regg R3(ck, rst, res, ls, RegS);

    assign resultado = RegS;

endmodule

controle.v
module controle (
    input ck,
    input inicio,
    input rst,
    output reg lx,
    output reg [1:0] m0,
    output reg [1:0] m1,
    output reg [1:0] m2,
    output reg h,
    output reg ls,
    output reg lh,
    output reg pronto
);

reg [3:0] state = 4'b0000; // inicializa em A
parameter [3:0] A = 4'b0000, B = 4'b0001, C = 4'b0010, D = 4'b0011, E = 4'b0100, F = 4'b0101, G = 4'b0110, H = 4'b0111, I = 4'b1000, J = 4'b1001;


always @(posedge ck or rst) begin //Clock na borda de subida
    if(rst == 1) begin
        state <= A;
    end
    else begin
        case (state)
            A : begin
                lx <= 1'b0; 
                m0 <= 2'b00;
                m1 <= 2'b00;
                m2 <= 2'b00;
                h <= 1'b0; 
                ls <= 1'b0;
                lh <= 1'b0;
                pronto <= 1'b0;
                if(inicio == 1) begin
                    state <= B;
                end
                else begin
                    state <= A;
                end
            end
            B : begin
                lx <= 1'b1; 
                m0 <= 2'b01; 
                m1 <= 2'b00;
                m2 <= 2'b00; 
                h <= 1'b1; 
                ls <= 1'b0; 
                lh <= 1'b0; 
                pronto <= 1'b0;
                state <= C;
            end
            C : begin
                lx <= 1'b0;
                m0 <= 2'b01;
                m1 <= 2'b00;
                m2 <= 2'b00;
                h <= 1'b1;
                ls <= 1'b0;
                lh <= 1'b1;
                pronto <= 1'b0;
                state <= D;
            end
            D : begin
                lx <= 1'b0;
                m0 <= 2'b10;
                m1 <= 2'b00;
                m2 <= 2'b11;
                h <= 1'b0;
                ls <= 1'b0;
                lh <= 1'b0;
                pronto <= 1'b0;
                state <= E;
            end
            E : begin
                lx <= 1'b0;
                m0 <= 2'b10;
                m1 <= 2'b00;
                m2 <= 2'b11;
                h <= 1'b0;
                ls <= 1'b0;
                lh <= 1'b1;
                pronto <= 1'b0;
                state <= F;
            end
            F : begin
                lx <= 1'b0;
                m0 <= 2'b00;
                m1 <= 2'b01;
                m2 <= 2'b11;
                h <= 1'b1;
                ls <= 1'b0;
                lh <= 1'b0;
                pronto <= 1'b0;
                state <= G;
            end
            G : begin
                lx <= 1'b0;
                m0 <= 2'b00;
                m1 <= 2'b01;
                m2 <= 2'b11;
                h <= 1'b1;
                ls <= 1'b0;
                lh <= 1'b1;
                pronto <= 1'b0;
                state <= H;
            end
            H : begin
                lx <= 1'b0;
                m0 <= 2'b11;
                m1 <= 2'b00;
                m2 <= 2'b11;
                h <= 1'b0;
                ls <= 1'b0;
                lh <= 1'b0;
                pronto <= 1'b0;
                state <= I;
            end
            I : begin
                lx <= 1'b0;
                m0 <= 2'b11;
                m1 <= 2'b00;
                m2 <= 2'b11;
                h <= 1'b0;
                ls <= 1'b1;
                lh <= 1'b0;
                pronto <= 1'b0;
                state <= J;
            end
            J : begin
                lx <= 1'b0;
                m0 <= 2'b00;
                m1 <= 2'b00;
                m2 <= 2'b00;
                h <= 1'b0;
                ls <= 1'b0;
                lh <= 1'b0;
                pronto <= 1'b1;
                state <= A;
            end
        endcase    
    end
end
endmodule

projeto.v
module projeto(
    input ck,
    input inicio,
    input rst,
    input [15:0] X,
    input [15:0] A,
    input [15:0] B,
    input [15:0] C,
    output pronto,
    output overflow,
    output [15:0] resultado
);

    wire lx, h, ls, lh;
    wire [1:0] m0, m1, m2; 

    controle c(ck, inicio, rst, lx, m0, m1, m2, h, ls, lh, pronto);
    operativo op(ck, rst, lx, m0, m1, m2, h, ls, lh, X, A, B, C, pronto, overflow, resultado);

endmodule

testbench.v
module testbench;

    parameter [15:0] X = 16'b0000000000010111;
    parameter [15:0] A = 16'b0000000000100110;
    parameter [15:0] B = 16'b0000000101001101;
    parameter [15:0] C = 16'b0001001100100110;
    
    reg ck = 1'b0;
    reg inicio;
    reg rst;
    wire pronto;
    wire overflow;
    wire [15:0] resultado;

    projeto p(ck, inicio, rst, X, A, B, C, pronto, overflow, resultado);

    always #1 begin
        ck <= ~ck;
    end

    initial begin
        $dumpvars;
        inicio <= 0;
        rst <= 0;
        #2;
        inicio <= 1;
        #2;
        inicio <= 0;
        #25;
        rst <= 1;
        #2
        rst <= 0;
        $finish;
    end


endmodule

dump.vcd
$date
	Thu May 13 11:06:01 2021
$end
$version
	Icarus Verilog
$end
$timescale
	1s
$end
$scope module testbench $end
$var wire 16 ! resultado [15:0] $end
$var wire 1 " pronto $end
$var wire 1 # overflow $end
$var reg 1 $ ck $end
$var reg 1 % inicio $end
$var reg 1 & rst $end
$scope module p $end
$var wire 16 ' A [15:0] $end
$var wire 16 ( B [15:0] $end
$var wire 16 ) C [15:0] $end
$var wire 16 * X [15:0] $end
$var wire 1 $ ck $end
$var wire 1 % inicio $end
$var wire 1 & rst $end
$var wire 16 + resultado [15:0] $end
$var wire 1 " pronto $end
$var wire 1 # overflow $end
$var wire 2 , m2 [1:0] $end
$var wire 2 - m1 [1:0] $end
$var wire 2 . m0 [1:0] $end
$var wire 1 / lx $end
$var wire 1 0 ls $end
$var wire 1 1 lh $end
$var wire 1 2 h $end
$scope module c $end
$var wire 1 $ ck $end
$var wire 1 % inicio $end
$var wire 1 & rst $end
$var reg 1 2 h $end
$var reg 1 1 lh $end
$var reg 1 0 ls $end
$var reg 1 / lx $end
$var reg 2 3 m0 [1:0] $end
$var reg 2 4 m1 [1:0] $end
$var reg 2 5 m2 [1:0] $end
$var reg 1 " pronto $end
$var reg 4 6 state [3:0] $end
$upscope $end
$scope module op $end
$var wire 16 7 A [15:0] $end
$var wire 16 8 B [15:0] $end
$var wire 16 9 C [15:0] $end
$var wire 16 : X [15:0] $end
$var wire 1 $ ck $end
$var wire 1 2 h $end
$var wire 1 1 lh $end
$var wire 1 0 ls $end
$var wire 1 / lx $end
$var wire 2 ; m0 [1:0] $end
$var wire 2 < m1 [1:0] $end
$var wire 2 = m2 [1:0] $end
$var wire 1 " pronto $end
$var wire 16 > resultado [15:0] $end
$var wire 1 & rst $end
$var wire 16 ? res [15:0] $end
$var wire 1 # overflow $end
$var wire 16 @ outm2 [15:0] $end
$var wire 16 A outm1 [15:0] $end
$var wire 16 B outm0 [15:0] $end
$var wire 16 C RegX [15:0] $end
$var wire 16 D RegS [15:0] $end
$var wire 16 E RegH [15:0] $end
$scope module M0 $end
$var wire 16 F a [15:0] $end
$var wire 16 G b [15:0] $end
$var wire 16 H c [15:0] $end
$var wire 16 I d [15:0] $end
$var wire 2 J sel [1:0] $end
$var reg 16 K out [15:0] $end
$upscope $end
$scope module M1 $end
$var wire 16 L a [15:0] $end
$var wire 2 M sel [1:0] $end
$var wire 16 N d [15:0] $end
$var wire 16 O c [15:0] $end
$var wire 16 P b [15:0] $end
$var reg 16 Q out [15:0] $end
$upscope $end
$scope module M2 $end
$var wire 16 R b [15:0] $end
$var wire 2 S sel [1:0] $end
$var wire 16 T d [15:0] $end
$var wire 16 U c [15:0] $end
$var wire 16 V a [15:0] $end
$var reg 16 W out [15:0] $end
$upscope $end
$scope module R1 $end
$var wire 1 $ ck $end
$var wire 1 / l $end
$var wire 1 & rst $end
$var wire 16 X v [15:0] $end
$var reg 16 Y r [15:0] $end
$upscope $end
$scope module R2 $end
$var wire 1 $ ck $end
$var wire 1 0 l $end
$var wire 1 & rst $end
$var wire 16 Z v [15:0] $end
$var reg 16 [ r [15:0] $end
$upscope $end
$scope module R3 $end
$var wire 1 $ ck $end
$var wire 1 1 l $end
$var wire 1 & rst $end
$var wire 16 \ v [15:0] $end
$var reg 16 ] r [15:0] $end
$upscope $end
$scope module U $end
$var wire 1 2 h $end
$var wire 16 ^ v1 [15:0] $end
$var wire 16 _ v2 [15:0] $end
$var reg 1 # overflow $end
$var reg 16 ` r [15:0] $end
$upscope $end
$upscope $end
$upscope $end
$upscope $end
$enddefinitions $end
#0
$dumpvars
bx `
bx _
b0 ^
bx ]
bx \
bx [
bx Z
bx Y
b10111 X
bx W
bx V
bx U
bx T
b0 S
b0 R
b0 Q
bx P
bx O
bx N
b0 M
b0 L
b0 K
b0 J
b1001100100110 I
b101001101 H
b100110 G
b0 F
bx E
bx D
bx C
b0 B
b0 A
bx @
bx ?
bx >
b0 =
b0 <
b0 ;
b10111 :
b1001100100110 9
b101001101 8
b100110 7
b0 6
b0 5
b0 4
b0 3
02
01
00
0/
b0 .
b0 -
b0 ,
bx +
b10111 *
b1001100100110 )
b101001101 (
b100110 '
0&
0%
0$
x#
0"
bx !
$end
#1
1$
#2
0$
1%
#3
b1 6
1$
#4
0$
0%
#5
b100110 A
b100110 Q
b100110 ^
b100110 B
b100110 K
b100110 L
b100110 R
b10 6
12
b1 .
b1 3
b1 ;
b1 J
1/
1$
#6
0$
#7
b11 6
11
0/
0#
b1101101010 ?
b1101101010 Z
b1101101010 \
b1101101010 `
b10111 @
b10111 W
b10111 _
b10111 C
b10111 P
b10111 V
b10111 Y
1$
#8
0$
#9
b101001101 A
b101001101 Q
b101001101 ^
b10010110111 ?
b10010110111 Z
b10010110111 \
b10010110111 `
b1101101010 @
b1101101010 W
b1101101010 _
b101001101 B
b101001101 K
b101001101 L
b101001101 R
b100 6
01
02
b11 ,
b11 5
b11 =
b11 S
b10 .
b10 3
b10 ;
b10 J
b1101101010 E
b1101101010 N
b1101101010 T
b1101101010 ]
1$
#10
0$
#11
b101 6
11
1$
#12
0$
#13
b10111 A
b10111 Q
b10111 ^
b0 B
b0 K
b0 L
b0 R
b110 6
01
12
b1 -
b1 4
b1 <
b1 M
b0 .
b0 3
b0 ;
b0 J
b110110001110001 ?
b110110001110001 Z
b110110001110001 \
b110110001110001 `
b10010110111 @
b10010110111 W
b10010110111 _
b10010110111 E
b10010110111 N
b10010110111 T
b10010110111 ]
1$
#14
0$
#15
b111 6
11
1$
#16
0$
#17
b1001100100110 A
b1001100100110 Q
b1001100100110 ^
b1001100100110 B
b1001100100110 K
b1001100100110 L
b1001100100110 R
b1000 6
01
02
b0 -
b0 4
b0 <
b0 M
b11 .
b11 3
b11 ;
b11 J
0#
b111111110010111 ?
b111111110010111 Z
b111111110010111 \
b111111110010111 `
b110110001110001 @
b110110001110001 W
b110110001110001 _
b110110001110001 E
b110110001110001 N
b110110001110001 T
b110110001110001 ]
1$
#18
0$
#19
b1001 6
10
1$
#20
0$
#21
b10111 ?
b10111 Z
b10111 \
b10111 `
b0 A
b0 Q
b0 ^
b10111 @
b10111 W
b10111 _
b0 B
b0 K
b0 L
b0 R
b0 6
1"
00
b0 ,
b0 5
b0 =
b0 S
b0 .
b0 3
b0 ;
b0 J
b111111110010111 !
b111111110010111 +
b111111110010111 >
b111111110010111 D
b111111110010111 O
b111111110010111 U
b111111110010111 [
1$
#22
0$
#23
0"
1$
#24
0$
#25
1$
#26
0$
#27
1$
#28
0$
#29
b0 ?
b0 Z
b0 \
b0 `
b0 @
b0 W
b0 _
b0 C
b0 P
b0 V
b0 Y
b0 !
b0 +
b0 >
b0 D
b0 O
b0 U
b0 [
b0 E
b0 N
b0 T
b0 ]
1$
1&
#30
0$
#31
1$
0&
